okane.py
okane-0.2.0.dist-info/LICENSE.txt
okane-0.2.0.dist-info/METADATA
okane-0.2.0.dist-info/WHEEL
okane-0.2.0.dist-info/entry_points.txt
okane-0.2.0.dist-info/RECORD
