Metadata-Version: 2.1
Name: okane
Version: 0.2.0
Summary: Parser for bank statements in camt.053 XML format (Czech Banking Association dialect)
Home-page: https://github.com/tkarabela/okane
License: MIT
Keywords: finance,czech,banking,sepa,expenses,camt053
Author: Tomas Karabela
Author-email: tkarabela@seznam.cz
Requires-Python: >=3.10,<4.0
Classifier: Development Status :: 3 - Alpha
Classifier: Intended Audience :: Financial and Insurance Industry
Classifier: License :: OSI Approved :: MIT License
Classifier: Operating System :: OS Independent
Classifier: Programming Language :: Python :: 3
Classifier: Programming Language :: Python :: 3.10
Classifier: Programming Language :: Python :: 3.11
Classifier: Programming Language :: Python :: 3.12
Classifier: Topic :: File Formats
Classifier: Topic :: Office/Business :: Financial :: Accounting
Classifier: Typing :: Typed
Provides-Extra: pandas
Requires-Dist: lxml (>=4.9,<5.0)
Requires-Dist: openpyxl (>=3.1,<4.0) ; extra == "pandas"
Requires-Dist: pandas (>=2.1,<3.0) ; extra == "pandas"
Requires-Dist: pydantic (>=2.5,<3.0)
Project-URL: Bug Tracker, https://github.com/tkarabela/okane/issues
Project-URL: Repository, https://github.com/tkarabela/okane
